CHANGELOG.txt
LICENCE.txt
MANIFEST.in
README.txt
__init__.py
setup.py
sripadhsujith.egg-info/PKG-INFO
sripadhsujith.egg-info/SOURCES.txt
sripadhsujith.egg-info/dependency_links.txt
sripadhsujith.egg-info/top_level.txt
venv/Lib/site-packages/_virtualenv.py
venv/Lib/site-packages/pythoncom.py
venv/Lib/site-packages/pywin32.version.txt
venv/Lib/site-packages/six.py
venv/Lib/site-packages/zipp.py
venv/Lib/site-packages/Pygments-2.10.0.dist-info/entry_points.txt
venv/Lib/site-packages/Pygments-2.10.0.dist-info/top_level.txt
venv/Lib/site-packages/_distutils_hack/__init__.py
venv/Lib/site-packages/_distutils_hack/override.py
venv/Lib/site-packages/adodbapi/__init__.py
venv/Lib/site-packages/adodbapi/ado_consts.py
venv/Lib/site-packages/adodbapi/adodbapi.py
venv/Lib/site-packages/adodbapi/apibase.py
venv/Lib/site-packages/adodbapi/is64bit.py
venv/Lib/site-packages/adodbapi/license.txt
venv/Lib/site-packages/adodbapi/process_connect_string.py
venv/Lib/site-packages/adodbapi/readme.txt
venv/Lib/site-packages/adodbapi/remote.py
venv/Lib/site-packages/adodbapi/schema_table.py
venv/Lib/site-packages/adodbapi/setup.py
venv/Lib/site-packages/adodbapi/examples/db_print.py
venv/Lib/site-packages/adodbapi/examples/db_table_names.py
venv/Lib/site-packages/adodbapi/examples/xls_read.py
venv/Lib/site-packages/adodbapi/examples/xls_write.py
venv/Lib/site-packages/adodbapi/test/adodbapitest.py
venv/Lib/site-packages/adodbapi/test/adodbapitestconfig.py
venv/Lib/site-packages/adodbapi/test/dbapi20.py
venv/Lib/site-packages/adodbapi/test/is64bit.py
venv/Lib/site-packages/adodbapi/test/setuptestframework.py
venv/Lib/site-packages/adodbapi/test/test_adodbapi_dbapi20.py
venv/Lib/site-packages/adodbapi/test/tryconnection.py
venv/Lib/site-packages/beautifulsoup4-4.10.0.dist-info/COPYING.txt
venv/Lib/site-packages/beautifulsoup4-4.10.0.dist-info/top_level.txt
venv/Lib/site-packages/bleach/__init__.py
venv/Lib/site-packages/bleach/callbacks.py
venv/Lib/site-packages/bleach/html5lib_shim.py
venv/Lib/site-packages/bleach/linkifier.py
venv/Lib/site-packages/bleach/sanitizer.py
venv/Lib/site-packages/bleach/utils.py
venv/Lib/site-packages/bleach-4.1.0.dist-info/top_level.txt
venv/Lib/site-packages/bleach/_vendor/__init__.py
venv/Lib/site-packages/bleach/_vendor/parse.py
venv/Lib/site-packages/bleach/_vendor/vendor.txt
venv/Lib/site-packages/bleach/_vendor/html5lib/__init__.py
venv/Lib/site-packages/bleach/_vendor/html5lib/_ihatexml.py
venv/Lib/site-packages/bleach/_vendor/html5lib-1.1.dist-info/top_level.txt
venv/Lib/site-packages/certifi-2021.10.8.dist-info/top_level.txt
venv/Lib/site-packages/charset_normalizer-2.0.9.dist-info/entry_points.txt
venv/Lib/site-packages/charset_normalizer-2.0.9.dist-info/top_level.txt
venv/Lib/site-packages/colorama-0.4.4.dist-info/LICENSE.txt
venv/Lib/site-packages/colorama-0.4.4.dist-info/top_level.txt
venv/Lib/site-packages/comtypes-1.1.10.dist-info/LICENSE.txt
venv/Lib/site-packages/comtypes-1.1.10.dist-info/top_level.txt
venv/Lib/site-packages/docutils-0.18.1.dist-info/COPYING.txt
venv/Lib/site-packages/docutils-0.18.1.dist-info/top_level.txt
venv/Lib/site-packages/idna-3.3.dist-info/top_level.txt
venv/Lib/site-packages/importlib_metadata-4.10.0.dist-info/top_level.txt
venv/Lib/site-packages/keyring-23.4.0.dist-info/entry_points.txt
venv/Lib/site-packages/keyring-23.4.0.dist-info/top_level.txt
venv/Lib/site-packages/packaging-21.3.dist-info/top_level.txt
venv/Lib/site-packages/pip-21.1.2.dist-info/LICENSE.txt
venv/Lib/site-packages/pip-21.1.2.dist-info/entry_points.txt
venv/Lib/site-packages/pip-21.1.2.dist-info/top_level.txt
venv/Lib/site-packages/pkginfo-1.8.2.dist-info/LICENSE.txt
venv/Lib/site-packages/pkginfo-1.8.2.dist-info/entry_points.txt
venv/Lib/site-packages/pkginfo-1.8.2.dist-info/top_level.txt
venv/Lib/site-packages/pyparsing-3.0.6.dist-info/top_level.txt
venv/Lib/site-packages/pypiwin32-223.dist-info/top_level.txt
venv/Lib/site-packages/pyttsx3-2.90.dist-info/top_level.txt
venv/Lib/site-packages/pywin32-303.dist-info/top_level.txt
venv/Lib/site-packages/pywin32_ctypes-0.2.0.dist-info/LICENSE.txt
venv/Lib/site-packages/pywin32_ctypes-0.2.0.dist-info/top_level.txt
venv/Lib/site-packages/readme_renderer-32.0.dist-info/entry_points.txt
venv/Lib/site-packages/readme_renderer-32.0.dist-info/top_level.txt
venv/Lib/site-packages/requests-2.26.0.dist-info/top_level.txt
venv/Lib/site-packages/requests_toolbelt-0.9.1.dist-info/top_level.txt
venv/Lib/site-packages/rfc3986-1.5.0.dist-info/top_level.txt
venv/Lib/site-packages/setuptools-57.0.0.dist-info/dependency_links.txt
venv/Lib/site-packages/setuptools-57.0.0.dist-info/entry_points.txt
venv/Lib/site-packages/setuptools-57.0.0.dist-info/top_level.txt
venv/Lib/site-packages/six-1.16.0.dist-info/top_level.txt
venv/Lib/site-packages/soupsieve-2.3.1.dist-info/top_level.txt
venv/Lib/site-packages/tqdm-4.62.3.dist-info/entry_points.txt
venv/Lib/site-packages/tqdm-4.62.3.dist-info/top_level.txt
venv/Lib/site-packages/twine-3.7.1.dist-info/entry_points.txt
venv/Lib/site-packages/twine-3.7.1.dist-info/top_level.txt
venv/Lib/site-packages/urllib3-1.26.7.dist-info/LICENSE.txt
venv/Lib/site-packages/urllib3-1.26.7.dist-info/top_level.txt
venv/Lib/site-packages/webencodings-0.5.1.dist-info/top_level.txt
venv/Lib/site-packages/wheel-0.36.2.dist-info/LICENSE.txt
venv/Lib/site-packages/wheel-0.36.2.dist-info/entry_points.txt
venv/Lib/site-packages/wheel-0.36.2.dist-info/top_level.txt
venv/Lib/site-packages/wikipedia-1.4.0.dist-info/top_level.txt
venv/Lib/site-packages/zipp-3.6.0.dist-info/top_level.txt
