Metadata-Version: 2.1
Name: sripadhsujith
Version: 0.0.1
Summary: A very useful pacakage
Home-page: UNKNOWN
Author: sripadhsujith
Author-email: sripadsujith@gmail.com
License: MIT
Keywords: wikipedia
Platform: UNKNOWN
Classifier: Development Status :: 5 - Production/Stable
Classifier: Intended Audience :: Education
Classifier: Operating System :: Microsoft :: Windows :: Windows 10
Classifier: License :: OSI Approved :: MIT License
Classifier: Programming Language :: Python :: 3
License-File: LICENCE.txt
